README.rst
setup.cfg
setup.py
lbryschema/__init__.py
lbryschema/address.py
lbryschema/base.py
lbryschema/claim.py
lbryschema/decode.py
lbryschema/encoding.py
lbryschema/error.py
lbryschema/fee.py
lbryschema/hashing.py
lbryschema/signer.py
lbryschema/uri.py
lbryschema/validator.py
lbryschema.egg-info/PKG-INFO
lbryschema.egg-info/SOURCES.txt
lbryschema.egg-info/dependency_links.txt
lbryschema.egg-info/requires.txt
lbryschema.egg-info/top_level.txt
lbryschema/legacy/StructuredDict.py
lbryschema/legacy/__init__.py
lbryschema/legacy/metadata_schemas.py
lbryschema/legacy/migrate.py
lbryschema/proto/__init__.py
lbryschema/proto/certificate_pb2.py
lbryschema/proto/claim_pb2.py
lbryschema/proto/fee_pb2.py
lbryschema/proto/metadata_pb2.py
lbryschema/proto/signature_pb2.py
lbryschema/proto/source_pb2.py
lbryschema/proto/stream_pb2.py
lbryschema/schema/__init__.py
lbryschema/schema/certificate.py
lbryschema/schema/claim.py
lbryschema/schema/fee.py
lbryschema/schema/metadata.py
lbryschema/schema/schema.py
lbryschema/schema/signature.py
lbryschema/schema/source.py
lbryschema/schema/stream.py