Metadata-Version: 1.0
Name: lbryschema
Version: 0.0.16
Summary: Protobuf schema for claims on the LBRY blockchain
Home-page: UNKNOWN
Author: jackrobison@lbry.io
Author-email: UNKNOWN
License: UNKNOWN
Platform: UNKNOWN
